{
  "placeholderImages": [
    {
      "id": "hero-sofa",
      "description": "Modern living room with a clean sofa",
      "imageUrl": "https://picsum.photos/seed/sofa1/1920/1080",
      "imageHint": "sofa living room"
    },
    {
      "id": "about-team",
      "description": "Smiling and professional cleaning team",
      "imageUrl": "https://picsum.photos/seed/team1/600/400",
      "imageHint": "team professional"
    },
    {
      "id": "testimonial-1",
      "description": "Portrait of a happy customer",
      "imageUrl": "https://picsum.photos/seed/customer1/100/100",
      "imageHint": "person portrait"
    },
    {
      "id": "testimonial-2",
      "description": "Portrait of a happy customer",
      "imageUrl": "https://picsum.photos/seed/customer2/100/100",
      "imageHint": "person portrait"
    },
    {
      "id": "testimonial-3",
      "description": "Portrait of a happy customer",
      "imageUrl": "https://picsum.photos/seed/customer3/100/100",
      "imageHint": "person portrait"
    }
  ]
}
